pfx_insights/__init__.py
pfx_insights/convertToSynapseNotebook.py
pfx_insights/feature_generation_utils.py
pfx_insights/html_utils.py
pfx_insights/interpret_utils.py
pfx_insights/json_to_table.py
pfx_insights/nlp_helpers.py
pfx_insights/text_utils.py
pfx_insights/resources/bing_stopwords.txt
tests/__init__.py
tests/test_feature_generation_utils.py
pfx_insights-0.2.0.dist-info/LICENSE
pfx_insights-0.2.0.dist-info/METADATA
pfx_insights-0.2.0.dist-info/WHEEL
pfx_insights-0.2.0.dist-info/top_level.txt
pfx_insights-0.2.0.dist-info/RECORD
