Metadata-Version: 2.1
Name: pfx-insights
Version: 0.2.0
Summary: Reusable python utilities for PFX Insights team
Home-page: https://github.com/pypa/sampleproject
Author: PX PACE Insights
Author-email: px-pace-insights@microsoft.com
License: UNKNOWN
Platform: UNKNOWN
Classifier: Programming Language :: Python :: 3
Classifier: License :: OSI Approved :: MIT License
Classifier: Operating System :: OS Independent
Requires-Python: >=3.6
License-File: LICENSE
